README.rst
setup.py
SafeRLBench/__init__.py
SafeRLBench/base.py
SafeRLBench/bench.py
SafeRLBench/configuration.py
SafeRLBench/error.py
SafeRLBench/measure.py
SafeRLBench/monitor.py
SafeRLBench.egg-info/PKG-INFO
SafeRLBench.egg-info/SOURCES.txt
SafeRLBench.egg-info/dependency_links.txt
SafeRLBench.egg-info/requires.txt
SafeRLBench.egg-info/top_level.txt
SafeRLBench/algo/__init__.py
SafeRLBench/algo/a3c.py
SafeRLBench/algo/policygradient.py
SafeRLBench/algo/q_learning.py
SafeRLBench/algo/safeopt.py
SafeRLBench/algo/test.py
SafeRLBench/envs/__init__.py
SafeRLBench/envs/general_mountaincar.py
SafeRLBench/envs/gym_wrap.py
SafeRLBench/envs/linear_car.py
SafeRLBench/envs/mdp.py
SafeRLBench/envs/quadrocopter.py
SafeRLBench/envs/test.py
SafeRLBench/policy/__init__.py
SafeRLBench/policy/controller.py
SafeRLBench/policy/linear_policy.py
SafeRLBench/policy/neural_network.py
SafeRLBench/policy/test.py
SafeRLBench/spaces/__init__.py
SafeRLBench/spaces/bounded_space.py
SafeRLBench/spaces/discrete_space.py
SafeRLBench/spaces/rd_space.py
SafeRLBench/spaces/test.py