Metadata-Version: 1.0
Name: SafeRLBench
Version: 1.0.1
Summary: Safe Reinforcement Learning Benchmark
Home-page: https://github.com/befelix/Safe-RL-Benchmark
Author: Nicolas Ochsner
Author-email: ochsnern@student.ethz.ch
License: UNKNOWN
Keywords: reinforcement-learning benchmark
Platform: UNKNOWN
